aioli_guestbook/__init__.py
aioli_guestbook/config.py
aioli_guestbook/controller.py
aioli_guestbook/database.py
aioli_guestbook/schema.py
aioli_guestbook/service/__init__.py
aioli_guestbook/service/visit.py
aioli_guestbook/service/visitor.py
aioli_guestbook-0.3.3.dist-info/LICENSE
aioli_guestbook-0.3.3.dist-info/WHEEL
aioli_guestbook-0.3.3.dist-info/METADATA
aioli_guestbook-0.3.3.dist-info/RECORD
