Metadata-Version: 2.1
Name: aioli-guestbook
Version: 0.3.3
Summary: Comprehensive RESTful HTTP API built on top of the Aioli Framework
Home-page: https://github.com/aioli-framework/aioli-guestbook-example
License: MIT
Keywords: aioli_package
Author: Robert Wikman
Author-email: rbw@vault13.org
Requires-Python: >=3.6,<4.0
Classifier: License :: OSI Approved :: MIT License
Classifier: Programming Language :: Python :: 3
Classifier: Programming Language :: Python :: 3.6
Classifier: Programming Language :: Python :: 3.7
Requires-Dist: aioli (>=0.5.0,<0.6.0)
Requires-Dist: aioli-rdbms (>=0.3.0,<0.4.0)
Requires-Dist: maxminddb-geolite2 (>=2018.703,<2019.0)
Requires-Dist: toml (>=0.10.0,<0.11.0)
